kikiutils/__init__.py
kikiutils/aes.py
kikiutils/aio.py
kikiutils/aiofile.py
kikiutils/check.py
kikiutils/cookie.py
kikiutils/decorators.py
kikiutils/file.py
kikiutils/hash.py
kikiutils/import_utils.py
kikiutils/json.py
kikiutils/log.py
kikiutils/network.py
kikiutils/string.py
kikiutils/time.py
kikiutils/typehint.py
kikiutils/uuid.py
kiki_utils-1.3.9.dist-info/LICENSE.txt
kiki_utils-1.3.9.dist-info/METADATA
kiki_utils-1.3.9.dist-info/WHEEL
kiki_utils-1.3.9.dist-info/top_level.txt
kiki_utils-1.3.9.dist-info/zip-safe
kiki_utils-1.3.9.dist-info/RECORD
