Metadata-Version: 2.1
Name: kiki-utils
Version: 1.3.9
Summary: Utils decorators and functions.
Author: kiki-kanri
Author-email: a470666@gmail.com
Keywords: Utils
Classifier: License :: Freely Distributable
Requires-Python: >=3.8
License-File: LICENSE.txt
Requires-Dist: aiofiles
Requires-Dist: aioshutil
Requires-Dist: loguru
Requires-Dist: orjson
Requires-Dist: pycryptodomex
Requires-Dist: pyopenssl
Requires-Dist: python-magic ; platform_system == "Linux"
Requires-Dist: python-magic-bin ; platform_system == "Windows"
